{
    "boxShadow": "none",
    "mobileBottomRow": 48,
    "widgetName": "context_Swtich",
    "displayName": "开关",
    "iconSVG": "/static/media/icon.afbd826fee9d09b12c5cde30a8c6fe62.svg",
    "searchTags": [
        "toggle",
        "switch"
    ],
    "topRow": 25,
    "bottomRow": 29,
    "parentRowSpace": 10,
    "type": "SWITCH_WIDGET",
    "alignWidget": "LEFT",
    "hideCard": false,
    "mobileRightColumn": 2,
    "shouldScrollContents": true,
    "animateLoading": false,
    "parentColumnSpace": 22.0625,
    "dynamicTriggerPathList": [],
    "leftColumn": 41,
    "dynamicBindingPathList": [{"key": "accentColor"}],
    "labelPosition": "Right",
    "labelStyle": "",
    "isDisabled": false,
    "key": "3ea8dikoug",
    "labelTextSize": "1rem",
    "isDeprecated": false,
    "rightColumn": 49,
    "dynamicHeight": "AUTO_HEIGHT",
    "widgetId": "wa5yu3hnya",
    "accentColor": "{{appsmith.theme.colors.primaryColor}}",
    "isVisible": false,
    "label": "启用上下文",
    "defaultSwitchState": false,
    "version": 1,
    "parentId": "dhyv0llqnt",
    "tags": ["选择器组件"],
    "renderMode": "CANVAS",
    "isLoading": false,
    "mobileTopRow": 44,
    "responsiveBehavior": "fill",
    "originalTopRow": 54,
    "mobileLeftColumn": 0,
    "maxDynamicHeight": 9000,
    "originalBottomRow": 58,
    "minDynamicHeight": 4
}