{
  "unpublishedPage": {
    "name": "诊断",
    "slug": "",
    "layouts": [
      {
        "viewMode": false,
        "dsl": {
          "widgetName": "MainContainer",
          "backgroundColor": "none",
          "rightColumn": 4896,
          "snapColumns": 64,
          "detachFromLayout": true,
          "widgetId": "0",
          "topRow": 0,
          "bottomRow": 1050,
          "containerStyle": "none",
          "snapRows": 124,
          "parentRowSpace": 1,
          "type": "CANVAS_WIDGET",
          "canExtend": true,
          "version": 89,
          "minHeight": 1292,
          "useAutoLayout": false,
          "dynamicTriggerPathList": [],
          "parentColumnSpace": 1,
          "dynamicBindingPathList": [],
          "leftColumn": 0,
          "positioning": "fixed"
        },
        "layoutOnLoadActions": [],
        "layoutOnLoadActionErrors": [],
        "validOnPageLoadActions": true,
        "id": "诊断",
        "deleted": false,
        "policies": [],
        "userPermissions": []
      }
    ],
    "userPermissions": [],
    "policies": [],
    "isHidden": false
  },
  "deleted": false,
  "gitSyncId": "688984c4f032bd71eea01831_6889dd85f032bd71eea0189e"
}